twbanker/__init__.py
twbanker/cli.py
twbanker/banks/__init__.py
twbanker/banks/chartered.py
twbanker/banks/ctbc.py
twbanker/banks/first.py
twbanker/banks/post.py
twbanker/banks/shinkong.py
twbanker-0.2.1.dist-info/DESCRIPTION.rst
twbanker-0.2.1.dist-info/entry_points.txt
twbanker-0.2.1.dist-info/METADATA
twbanker-0.2.1.dist-info/metadata.json
twbanker-0.2.1.dist-info/RECORD
twbanker-0.2.1.dist-info/top_level.txt
twbanker-0.2.1.dist-info/WHEEL
