Metadata-Version: 2.0
Name: twbanker
Version: 0.2.1
Summary: Show you the money in your Taiwan banks
Home-page: https://github.com/eliangcs/twbanker
Author: Chang-Hung Liang
Author-email: eliang.cs@gmail.com
License: MIT
Platform: UNKNOWN
Classifier: Development Status :: 2 - Pre-Alpha
Classifier: Environment :: Console
Classifier: Intended Audience :: Developers
Classifier: License :: OSI Approved :: MIT License
Classifier: Operating System :: OS Independent
Classifier: Programming Language :: Python
Classifier: Programming Language :: Python :: 2.7
Classifier: Topic :: Internet :: WWW/HTTP
Classifier: Topic :: Office/Business :: Financial :: Accounting
Requires-Dist: click (>=3.3,<3.4)
Requires-Dist: lxml (>=3.4.0,<3.5.0)
Requires-Dist: pycrypto (>=2.6.1,<2.7.0)
Requires-Dist: requests (>=2.5.0,<2.6.0)
Provides-Extra: dev
Requires-Dist: ipython; extra == 'dev'
